Metadata-Version: 2.1
Name: nonebot-plugin-ping
Version: 1.5.4
Summary: ping
Home-page: https://github.com/zhulinyv/nonebot_plugin_ping
Author: (๑•小丫头片子•๑)
Author-email: zhulinyv2005@outlook.com
License: MIT
Classifier: License :: OSI Approved :: MIT License
Classifier: Programming Language :: Python
Classifier: Programming Language :: Python :: 3
Classifier: Programming Language :: Python :: 3.6
Classifier: Programming Language :: Python :: Implementation :: CPython
Classifier: Programming Language :: Python :: Implementation :: PyPy
Requires-Python: >=3.6.0
License-File: LICENSE
Requires-Dist: nonebot2
Requires-Dist: nonebot-adapter-onebot
Requires-Dist: httpx
